[
  {
    "_id": "req001",
    "title": "서버 호스팅 비용 결제 요청",
    "content": "AWS 월간 호스팅 비용 (3월분) 청구",
    "team_name": "Team Alpha",
    "amount": 150000,
    "status": "pending",
    "request_date": "2026-04-15T09:00:00Z"
  },
  {
    "_id": "req002",
    "title": "시제품 제작용 3D 프린터 필라멘트 구매",
    "content": "PLA 필라멘트 10롤 구매 비용",
    "team_name": "Maker Bot",
    "amount": 200000,
    "status": "reviewing",
    "request_date": "2026-04-14T14:30:00Z"
  },
  {
    "_id": "req003",
    "title": "박람회 참가 부스 렌탈비",
    "content": "2026 스타트업 페스타 부스 B 타입",
    "team_name": "Visionary",
    "amount": 500000,
    "status": "approved",
    "request_date": "2026-04-10T10:15:00Z"
  },
  {
    "_id": "req004",
    "title": "[반려] 노트북 구매 요청 (개인용)",
    "content": "개발용 맥북 프로 M3 구매",
    "team_name": "Dev Squad",
    "amount": 3500000,
    "status": "rejected",
    "request_date": "2026-04-12T11:00:00Z"
  }
]
